{"resCd":"0000","rspMsg":"SUCCESS","result":{"info":{"comments":"","itemList":[{"itemNm":"[이벤트] 카드 재료 수집","itemList":[{"shopId":145,"resultItemId":128029,"resultItemNm":"New.2 변경권 상자 1개","probability":0.0500},{"shopId":145,"resultItemId":127754,"resultItemNm":"핑크 썸머 비눗방울 1개","probability":3.0000},{"shopId":145,"resultItemId":127742,"resultItemNm":"핑크 썸머 코스튬 박스 1개","probability":1.0000},{"shopId":145,"resultItemId":127685,"resultItemNm":"엔젤 베어 알약 1개","probability":3.0000},{"shopId":145,"resultItemId":127673,"resultItemNm":"엔젤 베어 코스튬 박스 1개","probability":1.0000},{"shopId":145,"resultItemId":127612,"resultItemNm":"자브의 보드판 리셋 쿠폰 1개","probability":6.4000},{"shopId":145,"resultItemId":127606,"resultItemNm":"자브의 보드판 쿠폰 1개","probability":14.5000},{"shopId":145,"resultItemId":127593,"resultItemNm":"애니멀 웨일 티켓 1개","probability":0.1000},{"shopId":145,"resultItemId":127587,"resultItemNm":"애니멀 웨일 코인 1개","probability":2.0000},{"shopId":145,"resultItemId":127581,"resultItemNm":"애니멀 웨일 상자 1개","probability":0.5000},{"shopId":145,"resultItemId":116281,"resultItemNm":"셀렉트샵 코인 1개","probability":8.0500},{"shopId":145,"resultItemId":108119,"resultItemNm":"생활 재료 교환권 1개","probability":30.2000},{"shopId":145,"resultItemId":108113,"resultItemNm":"전투 재료 교환권 1개","probability":30.2000},{"shopId":null,"resultItemId":null,"resultItemNm":"합계","probability":100.0000}]},{"itemNm":"[스페셜] 낡고 빛바랜 서약서","itemList":[{"shopId":140,"resultItemId":127124,"resultItemNm":"낡고 빛바랜 청첩장 2개","probability":25.0000},{"shopId":140,"resultItemId":127123,"resultItemNm":"낡고 빛바랜 청첩장 1개","probability":70.4690},{"shopId":140,"resultItemId":127111,"resultItemNm":"유령 신부의 면사포 1개","probability":0.0500},{"shopId":140,"resultItemId":127105,"resultItemNm":"유령 신부의 드레스 1개","probability":0.0500},{"shopId":140,"resultItemId":127099,"resultItemNm":"유령 신부의 티아라 1개","probability":0.0500},{"shopId":140,"resultItemId":127093,"resultItemNm":"유령 신부의 부케 1개","probability":0.0500},{"shopId":140,"resultItemId":127087,"resultItemNm":"유령 신부의 반지 1개","probability":0.0500},{"shopId":140,"resultItemId":127079,"resultItemNm":"유령 신부 내구도","probability":0.0010},{"shopId":140,"resultItemId":116235,"resultItemNm":"웨딩 글리터 발그레 내구도","probability":0.0600},{"shopId":140,"resultItemId":116231,"resultItemNm":"노이르 웨딩 크라운 내구도","probability":0.0600},{"shopId":140,"resultItemId":116229,"resultItemNm":"블랑슈 웨딩 크라운 내구도","probability":0.0600},{"shopId":140,"resultItemId":116227,"resultItemNm":"노이르 웨딩 리본 내구도","probability":0.0400},{"shopId":140,"resultItemId":116225,"resultItemNm":"블랑슈 웨딩 리본 내구도","probability":0.0400},{"shopId":140,"resultItemId":112094,"resultItemNm":"그레이스 웨딩 심볼 내구도","probability":0.0200},{"shopId":140,"resultItemId":112092,"resultItemNm":"체리쉬 웨딩 심볼 내구도","probability":0.0200},{"shopId":140,"resultItemId":112090,"resultItemNm":"그레이스 웨딩 화동 펫 내구도","probability":0.0200},{"shopId":140,"resultItemId":112088,"resultItemNm":"체리쉬 웨딩 화동 펫 내구도","probability":0.0200},{"shopId":140,"resultItemId":112086,"resultItemNm":"그레이스 웨딩 날개 내구도","probability":0.0200},{"shopId":140,"resultItemId":112084,"resultItemNm":"그레이스 웨딩 장갑 내구도","probability":0.0200},{"shopId":140,"resultItemId":112082,"resultItemNm":"그레이스 웨딩 머리장식 내구도","probability":0.0200},{"shopId":140,"resultItemId":112080,"resultItemNm":"그레이스 웨딩 슈즈 (여) 내구도","probability":0.0200},{"shopId":140,"resultItemId":112078,"resultItemNm":"그레이스 웨딩 슈즈 (남) 내구도","probability":0.0200},{"shopId":140,"resultItemId":112076,"resultItemNm":"그레이스 웨딩 드레스 (여) 내구도","probability":0.0200},{"shopId":140,"resultItemId":112074,"resultItemNm":"그레이스 웨딩 턱시도 (남) 내구도","probability":0.0200},{"shopId":140,"resultItemId":112072,"resultItemNm":"그레이스 웨딩 헤어 (여) 내구도","probability":0.0200},{"shopId":140,"resultItemId":112070,"resultItemNm":"그레이스 웨딩 헤어 (남) 내구도","probability":0.0200},{"shopId":140,"resultItemId":112068,"resultItemNm":"체리쉬 웨딩 날개 내구도","probability":0.0200},{"shopId":140,"resultItemId":112066,"resultItemNm":"체리쉬 웨딩 장갑 내구도","probability":0.0200},{"shopId":140,"resultItemId":112064,"resultItemNm":"체리쉬 웨딩 머리장식 내구도","probability":0.0200},{"shopId":140,"resultItemId":112062,"resultItemNm":"체리쉬 웨딩 슈즈 (여) 내구도","probability":0.0200},{"shopId":140,"resultItemId":112060,"resultItemNm":"체리쉬 웨딩 슈즈 (남) 내구도","probability":0.0200},{"shopId":140,"resultItemId":112058,"resultItemNm":"체리쉬 웨딩 드레스 (여) 내구도","probability":0.0200},{"shopId":140,"resultItemId":112056,"resultItemNm":"체리쉬 웨딩 턱시도 (남) 내구도","probability":0.0200},{"shopId":140,"resultItemId":112054,"resultItemNm":"체리쉬 웨딩 헤어 (여) 내구도","probability":0.0200},{"shopId":140,"resultItemId":112052,"resultItemNm":"체리쉬 웨딩 헤어 (남) 내구도","probability":0.0200},{"shopId":140,"resultItemId":104634,"resultItemNm":"청룡의 웨딩 베일 (여) 내구도","probability":0.0600},{"shopId":140,"resultItemId":104632,"resultItemNm":"청룡의 웨딩 반지 (여) 내구도","probability":0.0600},{"shopId":140,"resultItemId":104630,"resultItemNm":"청룡의 웨딩 슈즈 (여) 내구도","probability":0.0600},{"shopId":140,"resultItemId":104628,"resultItemNm":"청룡의 웨딩 드레스 (여) 내구도","probability":0.0600},{"shopId":140,"resultItemId":104626,"resultItemNm":"청룡의 웨딩 헤어 (여) 내구도","probability":0.0600},{"shopId":140,"resultItemId":104624,"resultItemNm":"청룡의 웨딩 마스크 (남) 내구도","probability":0.0600},{"shopId":140,"resultItemId":104622,"resultItemNm":"청룡의 웨딩 반지 (남) 내구도","probability":0.0600},{"shopId":140,"resultItemId":104620,"resultItemNm":"청룡의 웨딩 슈즈 (남) 내구도","probability":0.0600},{"shopId":140,"resultItemId":104618,"resultItemNm":"청룡의 웨딩 복장 (남) 내구도","probability":0.0600},{"shopId":140,"resultItemId":104616,"resultItemNm":"청룡의 웨딩 헤어 (남) 내구도","probability":0.0600},{"shopId":140,"resultItemId":84824,"resultItemNm":"팬텀 웨딩 얼굴 분장(여) 내구도","probability":0.0600},{"shopId":140,"resultItemId":84822,"resultItemNm":"팬텀 웨딩 얼굴 분장(남) 내구도","probability":0.0600},{"shopId":140,"resultItemId":84820,"resultItemNm":"팬텀 웨딩 헤어 장식(여) 내구도","probability":0.0600},{"shopId":140,"resultItemId":84818,"resultItemNm":"팬텀 웨딩 헤어 장식(남) 내구도","probability":0.0600},{"shopId":140,"resultItemId":84816,"resultItemNm":"팬텀 웨딩 슈즈(여) 내구도","probability":0.0600},{"shopId":140,"resultItemId":84814,"resultItemNm":"팬텀 웨딩 슈즈(남) 내구도","probability":0.0600},{"shopId":140,"resultItemId":84812,"resultItemNm":"팬텀 웨딩 드레스(여) 내구도","probability":0.0600},{"shopId":140,"resultItemId":84810,"resultItemNm":"팬텀 웨딩 수트(남) 내구도","probability":0.0600},{"shopId":140,"resultItemId":84808,"resultItemNm":"팬텀 웨딩 헤어(여) 내구도","probability":0.0600},{"shopId":140,"resultItemId":84806,"resultItemNm":"팬텀 웨딩 헤어(남) 내구도","probability":0.0600},{"shopId":140,"resultItemId":60601,"resultItemNm":"웨딩 리셉션 머리장식 내구도","probability":0.0800},{"shopId":140,"resultItemId":60599,"resultItemNm":"웨딩 리셉션 슈즈(여) 내구도","probability":0.0800},{"shopId":140,"resultItemId":60597,"resultItemNm":"웨딩 리셉션 드레스(여) 내구도","probability":0.0800},{"shopId":140,"resultItemId":60595,"resultItemNm":"웨딩 리셉션 헤어(여) 내구도","probability":0.0800},{"shopId":140,"resultItemId":60593,"resultItemNm":"웨딩 리셉션 슈즈(남) 내구도","probability":0.0800},{"shopId":140,"resultItemId":60591,"resultItemNm":"웨딩 리셉션 슈트(남) 내구도","probability":0.0800},{"shopId":140,"resultItemId":60589,"resultItemNm":"웨딩 리셉션 헤어(남) 내구도","probability":0.0800},{"shopId":140,"resultItemId":58483,"resultItemNm":"사브리나 웨딩 반지 내구도","probability":0.0800},{"shopId":140,"resultItemId":58481,"resultItemNm":"사브리나 웨딩 브로치 내구도","probability":0.0800},{"shopId":140,"resultItemId":58479,"resultItemNm":"사브리나 웨딩 슈즈 내구도","probability":0.0800},{"shopId":140,"resultItemId":58477,"resultItemNm":"사브리나 웨딩 드레스 내구도","probability":0.0800},{"shopId":140,"resultItemId":58475,"resultItemNm":"사브리나 웨딩 헤어 내구도","probability":0.0800},{"shopId":140,"resultItemId":58473,"resultItemNm":"앙리 웨딩 반지 내구도","probability":0.0800},{"shopId":140,"resultItemId":58471,"resultItemNm":"앙리 웨딩 부토니어 내구도","probability":0.0800},{"shopId":140,"resultItemId":58469,"resultItemNm":"앙리 웨딩 부츠 내구도","probability":0.0800},{"shopId":140,"resultItemId":58467,"resultItemNm":"앙리 웨딩 턱시도 내구도","probability":0.0800},{"shopId":140,"resultItemId":58465,"resultItemNm":"앙리 웨딩 헤어 내구도","probability":0.0800},{"shopId":140,"resultItemId":58463,"resultItemNm":"앙리의 결혼식 화동 내구도","probability":0.0800},{"shopId":140,"resultItemId":58453,"resultItemNm":"앙리 3세 펫 내구도","probability":0.0600},{"shopId":140,"resultItemId":42392,"resultItemNm":"블랙 웨딩신발(여) 내구도","probability":0.0800},{"shopId":140,"resultItemId":42390,"resultItemNm":"블랙 웨딩드레스(여) 내구도","probability":0.0800},{"shopId":140,"resultItemId":42388,"resultItemNm":"블랙 웨딩헤어(여) 내구도","probability":0.0800},{"shopId":140,"resultItemId":42386,"resultItemNm":"블랙 웨딩신발(남) 내구도","probability":0.0800},{"shopId":140,"resultItemId":42384,"resultItemNm":"블랙 웨딩하의(남) 내구도","probability":0.0800},{"shopId":140,"resultItemId":42382,"resultItemNm":"블랙 웨딩상의(남) 내구도","probability":0.0800},{"shopId":140,"resultItemId":42022,"resultItemNm":"웨딩 파티글러브A 내구도","probability":0.0600},{"shopId":140,"resultItemId":42020,"resultItemNm":"웨딩 파티슈즈A 내구도","probability":0.0600},{"shopId":140,"resultItemId":42018,"resultItemNm":"웨딩 파티룩A 내구도","probability":0.0600},{"shopId":140,"resultItemId":42016,"resultItemNm":"웨딩 파티헤어A 내구도","probability":0.0600},{"shopId":140,"resultItemId":42014,"resultItemNm":"웨딩 파티글러브S 내구도","probability":0.0400},{"shopId":140,"resultItemId":42012,"resultItemNm":"웨딩 파티슈즈S 내구도","probability":0.0400},{"shopId":140,"resultItemId":42010,"resultItemNm":"웨딩 파티룩S 내구도","probability":0.0400},{"shopId":140,"resultItemId":42008,"resultItemNm":"웨딩 파티헤어S 내구도","probability":0.0400},{"shopId":null,"resultItemId":null,"resultItemNm":"합계","probability":100.0000}]},{"itemNm":"[상시] 보석 교환소 (대)","itemList":[{"shopId":18,"resultItemId":109389,"resultItemNm":"보석 파편 100개","probability":100.0000},{"shopId":null,"resultItemId":null,"resultItemNm":"합계","probability":100.0000}]},{"itemNm":"[상시] 보석 교환소 (중)","itemList":[{"shopId":17,"resultItemId":109114,"resultItemNm":"보석 파편 10개","probability":100.0000},{"shopId":null,"resultItemId":null,"resultItemNm":"합계","probability":100.0000}]},{"itemNm":"[상시] 보석 교환소 (소)","itemList":[{"shopId":12,"resultItemId":109110,"resultItemNm":"보석 파편 1개","probability":100.0000},{"shopId":null,"resultItemId":null,"resultItemNm":"합계","probability":100.0000}]},{"itemNm":"[상시] 생활 재료 수집","itemList":[{"shopId":2,"resultItemId":116330,"resultItemNm":"악마의 낚싯대 1일","probability":3.5000},{"shopId":2,"resultItemId":115302,"resultItemNm":"황금 갯지렁이 10개","probability":3.0000},{"shopId":2,"resultItemId":112694,"resultItemNm":"2nd 다이아 체스트 1개","probability":0.0100},{"shopId":2,"resultItemId":108083,"resultItemNm":"낡은 광휘의 불꽃 상자 1개","probability":11.3000},{"shopId":2,"resultItemId":108077,"resultItemNm":"광휘의 불꽃 상자 1개","probability":0.1000},{"shopId":2,"resultItemId":97565,"resultItemNm":"4등급 아이템 복주머니 1개","probability":1.0000},{"shopId":2,"resultItemId":97520,"resultItemNm":"4등급 아이템 선택권 1개","probability":0.8700},{"shopId":2,"resultItemId":96015,"resultItemNm":"승리의 지렁이 3개","probability":1.2000},{"shopId":2,"resultItemId":92022,"resultItemNm":"푸른 장미검 낚싯대 1일","probability":3.5000},{"shopId":2,"resultItemId":92015,"resultItemNm":"매직 스타 낚싯대 1일","probability":3.5000},{"shopId":2,"resultItemId":89612,"resultItemNm":"천사의 낚싯대 1일","probability":3.5000},{"shopId":2,"resultItemId":83225,"resultItemNm":"여왕 지렁이 3개","probability":1.2000},{"shopId":2,"resultItemId":82531,"resultItemNm":"강화된 지니의 마법신발 내구도","probability":0.8700},{"shopId":2,"resultItemId":82529,"resultItemNm":"강화된 지니의 마법갑옷 내구도","probability":0.8700},{"shopId":2,"resultItemId":81283,"resultItemNm":"장군 지렁이 3개","probability":1.2000},{"shopId":2,"resultItemId":80711,"resultItemNm":"스포트라이트 내구도","probability":0.8700},{"shopId":2,"resultItemId":80709,"resultItemNm":"딜라이트 스타 윙 내구도","probability":0.8700},{"shopId":2,"resultItemId":80707,"resultItemNm":"딜라이트 스타 크라운 내구도","probability":0.8700},{"shopId":2,"resultItemId":80689,"resultItemNm":"밍쮸 내구도","probability":0.8700},{"shopId":2,"resultItemId":78643,"resultItemNm":"200% TR 포션 1개","probability":4.0000},{"shopId":2,"resultItemId":78637,"resultItemNm":"100% TR 포션 1개","probability":6.0000},{"shopId":2,"resultItemId":77682,"resultItemNm":"갯지렁이 훈제 구이 50개","probability":3.5000},{"shopId":2,"resultItemId":77678,"resultItemNm":"크릴 새우 필라프 100개","probability":3.5000},{"shopId":2,"resultItemId":77673,"resultItemNm":"삼각 주먹떡밥 100개","probability":3.5000},{"shopId":2,"resultItemId":58917,"resultItemNm":"100% 경험치 포션 1개","probability":6.0000},{"shopId":2,"resultItemId":58912,"resultItemNm":"200% 경험치 포션 1개","probability":4.0000},{"shopId":2,"resultItemId":58635,"resultItemNm":"다크니스 드래곤 부스터 내구도","probability":0.8700},{"shopId":2,"resultItemId":58631,"resultItemNm":"다크니스 드래곤 소울 내구도","probability":0.8700},{"shopId":2,"resultItemId":58627,"resultItemNm":"다크니스 드래곤 테일 내구도","probability":0.8700},{"shopId":2,"resultItemId":58623,"resultItemNm":"다크니스 드래곤 윙 내구도","probability":0.4300},{"shopId":2,"resultItemId":58619,"resultItemNm":"다크니스 드래곤 아이즈 내구도","probability":0.4300},{"shopId":2,"resultItemId":58615,"resultItemNm":"로드 오브 드래곤 내구도","probability":0.4300},{"shopId":2,"resultItemId":58141,"resultItemNm":"블러드 라이칸 윙 내구도","probability":0.8700},{"shopId":2,"resultItemId":58137,"resultItemNm":"블러드 라이칸 건틀릿 내구도","probability":0.8700},{"shopId":2,"resultItemId":58133,"resultItemNm":"블러드 라이칸 부츠 내구도","probability":0.8700},{"shopId":2,"resultItemId":58129,"resultItemNm":"블러드 라이칸 갑옷 내구도","probability":0.8700},{"shopId":2,"resultItemId":58125,"resultItemNm":"블러드 라이칸 머플러 내구도","probability":0.8700},{"shopId":2,"resultItemId":58121,"resultItemNm":"블러드 라이칸 투구 내구도","probability":0.8700},{"shopId":2,"resultItemId":56262,"resultItemNm":"러블리 플라워 부스터 내구도","probability":0.4300},{"shopId":2,"resultItemId":56246,"resultItemNm":"러블리 플라워 뱅글 내구도","probability":0.4300},{"shopId":2,"resultItemId":52551,"resultItemNm":"고대 드라칼 에그 1개","probability":0.8700},{"shopId":2,"resultItemId":52132,"resultItemNm":"확성기 부스터 내구도","probability":0.8700},{"shopId":2,"resultItemId":52130,"resultItemNm":"충전망치 뱅글 내구도","probability":0.8700},{"shopId":2,"resultItemId":52128,"resultItemNm":"파란 고래 내구도","probability":0.8700},{"shopId":2,"resultItemId":51835,"resultItemNm":"골드스타 부스터 내구도","probability":0.4300},{"shopId":2,"resultItemId":51831,"resultItemNm":"골드스타 넥아머 내구도","probability":0.4300},{"shopId":2,"resultItemId":51825,"resultItemNm":"영원의 피닉스 내구도","probability":0.4300},{"shopId":2,"resultItemId":49627,"resultItemNm":"다크니스 드래곤 에그 1개","probability":0.8700},{"shopId":2,"resultItemId":49625,"resultItemNm":"디바인 드래곤 에그 1개","probability":0.8700},{"shopId":2,"resultItemId":49623,"resultItemNm":"헬파이어 드래곤 에그 1개","probability":0.8700},{"shopId":2,"resultItemId":49313,"resultItemNm":"프로펠러 부스터 내구도","probability":0.8700},{"shopId":2,"resultItemId":49306,"resultItemNm":"전투력 측정 고글 내구도","probability":0.8700},{"shopId":2,"resultItemId":49299,"resultItemNm":"비행접시 내구도","probability":0.8700},{"shopId":2,"resultItemId":49012,"resultItemNm":"골든 카오스 머플러 내구도","probability":0.8700},{"shopId":2,"resultItemId":49005,"resultItemNm":"골든 카오스 마스크 내구도","probability":0.8700},{"shopId":2,"resultItemId":48998,"resultItemNm":"골든 카오스 부스터 내구도","probability":0.8700},{"shopId":2,"resultItemId":48991,"resultItemNm":"골든 카오스 윙 내구도","probability":0.4300},{"shopId":2,"resultItemId":48984,"resultItemNm":"골든 카오스 링 내구도","probability":0.4300},{"shopId":2,"resultItemId":46466,"resultItemNm":"배틀 머플러 내구도","probability":0.8700},{"shopId":2,"resultItemId":46459,"resultItemNm":"배틀 크라운 내구도","probability":0.8700},{"shopId":2,"resultItemId":46297,"resultItemNm":"레어 드래곤 에그 1개","probability":0.8700},{"shopId":2,"resultItemId":46295,"resultItemNm":"에이션트 드래곤 에그 1개","probability":0.8700},{"shopId":2,"resultItemId":46289,"resultItemNm":"배틀 기어 부스터 내구도","probability":0.8700},{"shopId":2,"resultItemId":46282,"resultItemNm":"배틀 볼 내구도","probability":0.8700},{"shopId":2,"resultItemId":46275,"resultItemNm":"배틀 마스크 내구도","probability":0.8700},{"shopId":2,"resultItemId":46268,"resultItemNm":"배틀 기어 내구도","probability":0.8700},{"shopId":null,"resultItemId":null,"resultItemNm":"합계","probability":100.0000}]},{"itemNm":"[상시] 전투 재료 수집","itemList":[{"shopId":1,"resultItemId":108071,"resultItemNm":"낡은 저주의 불꽃 상자 1개","probability":15.0263},{"shopId":1,"resultItemId":108065,"resultItemNm":"저주의 불꽃 상자 1개","probability":0.1503},{"shopId":1,"resultItemId":61203,"resultItemNm":"얼티밋 아쿤 내구도","probability":0.0751},{"shopId":1,"resultItemId":61197,"resultItemNm":"탈리아 부스터 내구도","probability":0.0751},{"shopId":1,"resultItemId":61193,"resultItemNm":"탈리아 뱅글 내구도","probability":0.0751},{"shopId":1,"resultItemId":61189,"resultItemNm":"탈리아 윙 내구도","probability":0.0751},{"shopId":1,"resultItemId":61187,"resultItemNm":"율리우스 윙 내구도","probability":0.0751},{"shopId":1,"resultItemId":61185,"resultItemNm":"율리우스 넥아머 내구도","probability":0.0751},{"shopId":1,"resultItemId":61183,"resultItemNm":"율리우스 글러브 내구도","probability":0.0751},{"shopId":1,"resultItemId":61181,"resultItemNm":"율리우스 슈즈 내구도","probability":0.0751},{"shopId":1,"resultItemId":61179,"resultItemNm":"율리우스 수트 내구도","probability":0.0751},{"shopId":1,"resultItemId":61177,"resultItemNm":"율리우스 헬멧 내구도","probability":0.0751},{"shopId":1,"resultItemId":57554,"resultItemNm":"엠퍼러가드 부스터 내구도","probability":0.0751},{"shopId":1,"resultItemId":57552,"resultItemNm":"엠퍼러가드 뱅글 내구도","probability":0.0751},{"shopId":1,"resultItemId":57550,"resultItemNm":"엠퍼러가드 윙 내구도","probability":0.0751},{"shopId":1,"resultItemId":57548,"resultItemNm":"엠퍼러가드 티아라(남) 내구도","probability":0.0751},{"shopId":1,"resultItemId":57546,"resultItemNm":"엠퍼러가드 티아라(여) 내구도","probability":0.0751},{"shopId":1,"resultItemId":57544,"resultItemNm":"엠퍼러가드 글러브(남) 내구도","probability":0.0751},{"shopId":1,"resultItemId":57542,"resultItemNm":"엠퍼러가드 글러브(여) 내구도","probability":0.0751},{"shopId":1,"resultItemId":57540,"resultItemNm":"엠퍼러가드 부츠(남) 내구도","probability":0.0751},{"shopId":1,"resultItemId":57538,"resultItemNm":"엠퍼러가드 부츠(여) 내구도","probability":0.0751},{"shopId":1,"resultItemId":57536,"resultItemNm":"엠퍼러가드 슈트(남) 내구도","probability":0.0751},{"shopId":1,"resultItemId":57534,"resultItemNm":"엠퍼러가드 슈트(여) 내구도","probability":0.0751},{"shopId":1,"resultItemId":57532,"resultItemNm":"엠퍼러가드 헤어(남) 내구도","probability":0.0751},{"shopId":1,"resultItemId":57530,"resultItemNm":"엠퍼러가드 헤어(여) 내구도","probability":0.0751},{"shopId":1,"resultItemId":53501,"resultItemNm":"분노한 코비 내구도","probability":0.0751},{"shopId":1,"resultItemId":53497,"resultItemNm":"스컬 팬텀 부스터 내구도","probability":0.0751},{"shopId":1,"resultItemId":53493,"resultItemNm":"스컬 팬텀 뱅글 내구도","probability":0.0751},{"shopId":1,"resultItemId":53487,"resultItemNm":"분노한 마리 내구도","probability":0.0751},{"shopId":1,"resultItemId":53485,"resultItemNm":"마리 내구도","probability":0.0751},{"shopId":1,"resultItemId":53388,"resultItemNm":"진 코멧 부스터 내구도","probability":0.7513},{"shopId":1,"resultItemId":53386,"resultItemNm":"코멧 부스터 내구도","probability":1.5026},{"shopId":1,"resultItemId":53382,"resultItemNm":"진 코멧 뱅글 내구도","probability":0.7513},{"shopId":1,"resultItemId":53380,"resultItemNm":"코멧 뱅글 내구도","probability":1.5026},{"shopId":1,"resultItemId":53376,"resultItemNm":"진 코멧 크라운 내구도","probability":0.7513},{"shopId":1,"resultItemId":53374,"resultItemNm":"코멧 크라운 내구도","probability":1.5026},{"shopId":1,"resultItemId":53370,"resultItemNm":"진 코멧 나이트 내구도","probability":1.5026},{"shopId":1,"resultItemId":53368,"resultItemNm":"코멧 나이트 내구도","probability":1.5026},{"shopId":1,"resultItemId":50864,"resultItemNm":"라이트 컴뱃 목걸이(진) 30일","probability":1.5026},{"shopId":1,"resultItemId":50859,"resultItemNm":"라이트 컴뱃 목걸이(금) 30일","probability":1.5026},{"shopId":1,"resultItemId":50854,"resultItemNm":"라이트 컴뱃 목걸이(은) 30일","probability":1.5026},{"shopId":1,"resultItemId":50816,"resultItemNm":"히든 컴뱃 링 내구도","probability":0.7513},{"shopId":1,"resultItemId":50814,"resultItemNm":"라이트 컴뱃 부스터 내구도","probability":1.5026},{"shopId":1,"resultItemId":50810,"resultItemNm":"라이트 컴뱃 브레이슬릿 내구도","probability":1.5026},{"shopId":1,"resultItemId":50806,"resultItemNm":"라이트 컴뱃 윙 내구도","probability":1.5026},{"shopId":1,"resultItemId":50802,"resultItemNm":"라이트 컴뱃 장갑 내구도","probability":1.5026},{"shopId":1,"resultItemId":50798,"resultItemNm":"라이트 컴뱃 부츠 내구도","probability":1.5026},{"shopId":1,"resultItemId":50794,"resultItemNm":"라이트 컴뱃 슈트 내구도","probability":1.5026},{"shopId":1,"resultItemId":50790,"resultItemNm":"라이트 컴뱃 헤어 내구도","probability":1.5026},{"shopId":1,"resultItemId":50786,"resultItemNm":"핑크 버터플라이 내구도","probability":1.5026},{"shopId":1,"resultItemId":50784,"resultItemNm":"블루 버터플라이 내구도","probability":1.5026},{"shopId":1,"resultItemId":50782,"resultItemNm":"컴뱃 버터플라이 내구도","probability":0.7513},{"shopId":1,"resultItemId":50460,"resultItemNm":"글라디오스 넥아머 내구도","probability":1.5026},{"shopId":1,"resultItemId":50458,"resultItemNm":"글라디오스 글러브 내구도","probability":1.5026},{"shopId":1,"resultItemId":50456,"resultItemNm":"글라디오스 슈즈 내구도","probability":1.5026},{"shopId":1,"resultItemId":50454,"resultItemNm":"글라디오스 수트 내구도","probability":1.5026},{"shopId":1,"resultItemId":50452,"resultItemNm":"글라디오스 헬멧 내구도","probability":1.5026},{"shopId":1,"resultItemId":50386,"resultItemNm":"스펠캐스트 방패 내구도","probability":1.5026},{"shopId":1,"resultItemId":50384,"resultItemNm":"스펠캐스트 글러브 내구도","probability":1.5026},{"shopId":1,"resultItemId":50382,"resultItemNm":"스펠캐스트 부츠 내구도","probability":1.5026},{"shopId":1,"resultItemId":50380,"resultItemNm":"스펠캐스트 갑옷 내구도","probability":1.5026},{"shopId":1,"resultItemId":50378,"resultItemNm":"스펠캐스트 투구 내구도","probability":1.5026},{"shopId":1,"resultItemId":50376,"resultItemNm":"저스티스 머플러 내구도","probability":0.7513},{"shopId":1,"resultItemId":50374,"resultItemNm":"저스티스 마스크 내구도","probability":0.7513},{"shopId":1,"resultItemId":50370,"resultItemNm":"저스티스 윙 내구도","probability":0.0751},{"shopId":1,"resultItemId":50366,"resultItemNm":"다크 아쿤 내구도","probability":0.7513},{"shopId":1,"resultItemId":41199,"resultItemNm":"블루리버 내구도","probability":0.7513},{"shopId":1,"resultItemId":41187,"resultItemNm":"블루리버의 눈빛 내구도","probability":0.7513},{"shopId":1,"resultItemId":41180,"resultItemNm":"베가 윙 내구도","probability":0.7513},{"shopId":1,"resultItemId":41178,"resultItemNm":"베가 머플러 내구도","probability":0.7513},{"shopId":1,"resultItemId":41176,"resultItemNm":"베가 마스크 내구도","probability":0.7513},{"shopId":1,"resultItemId":37241,"resultItemNm":"로열나이츠 부츠 내구도","probability":0.7513},{"shopId":1,"resultItemId":37239,"resultItemNm":"로열나이츠 글러브 내구도","probability":0.7513},{"shopId":1,"resultItemId":37237,"resultItemNm":"로열나이츠 슈트 내구도","probability":0.7513},{"shopId":1,"resultItemId":37235,"resultItemNm":"로열나이츠 헤어 내구도","probability":0.7513},{"shopId":1,"resultItemId":37233,"resultItemNm":"로열나이츠 티아라 내구도","probability":0.7513},{"shopId":1,"resultItemId":37231,"resultItemNm":"로열나이츠 팬던트 내구도","probability":0.7513},{"shopId":1,"resultItemId":37229,"resultItemNm":"슈페리어드 부츠 내구도","probability":1.5026},{"shopId":1,"resultItemId":37227,"resultItemNm":"슈페리어드 장갑 내구도","probability":1.5026},{"shopId":1,"resultItemId":37225,"resultItemNm":"슈페리어드 제복 내구도","probability":1.5026},{"shopId":1,"resultItemId":37223,"resultItemNm":"슈페리어드 모자 내구도","probability":1.5026},{"shopId":1,"resultItemId":35904,"resultItemNm":"다크 발키리 건틀릿 내구도","probability":1.5026},{"shopId":1,"resultItemId":35902,"resultItemNm":"흑기사 건틀릿 내구도","probability":1.5026},{"shopId":1,"resultItemId":35893,"resultItemNm":"다크 발키리 투구 내구도","probability":1.5026},{"shopId":1,"resultItemId":35891,"resultItemNm":"흑기사 투구 내구도","probability":1.5026},{"shopId":1,"resultItemId":35885,"resultItemNm":"다크 발키리 부츠 내구도","probability":1.5026},{"shopId":1,"resultItemId":35878,"resultItemNm":"흑기사 부츠 내구도","probability":1.5026},{"shopId":1,"resultItemId":35876,"resultItemNm":"다크 발키리 갑주 내구도","probability":1.5026},{"shopId":1,"resultItemId":35874,"resultItemNm":"흑기사 갑주 내구도","probability":1.5026},{"shopId":1,"resultItemId":35607,"resultItemNm":"스위티 아쿤 내구도","probability":1.5026},{"shopId":1,"resultItemId":35605,"resultItemNm":"마이티 아쿤 내구도","probability":0.7513},{"shopId":1,"resultItemId":35603,"resultItemNm":"타이니 아쿤 내구도","probability":1.5026},{"shopId":1,"resultItemId":35601,"resultItemNm":"아쿤 내구도","probability":1.5026},{"shopId":1,"resultItemId":35563,"resultItemNm":"데스머플러 내구도","probability":1.5026},{"shopId":1,"resultItemId":35561,"resultItemNm":"데스윙 내구도","probability":1.5026},{"shopId":1,"resultItemId":35559,"resultItemNm":"데스마스크 내구도","probability":1.5026},{"shopId":null,"resultItemId":null,"resultItemNm":"합계","probability":99.9975}]}]}}}